{
  "timestamp": "2025-06-30T19:36:39.301Z",
  "version": "1.0",
  "entries": [
    {
      "id": "entry_mcji2dfo_hkwncwdgg",
      "key": "swarm-auto-centralized-1751312065421/integration/implementation",
      "value": "\"INTEGRATION ANALYSIS COMPLETE\\n\\nCURRENT SYSTEM STATE:\\n- Frontend: Next.js on port 3000 with API routes in src/app/api/\\n- Backend: Python Flask service on port 5000 (backtrader-analysis)\\n- Environment: API keys configured (.env.local with Tiingo, Alpha Vantage, FRED, etc.)\\n- Docker: Python service has Dockerfile and docker-compose.yml\\n\\nCRITICAL INTEGRATION GAPS IDENTIFIED:\\n1. PORT MISMATCH: Python service runs on 5000, Next.js expects 5001\\n2. NO API PROXY: Next.js config lacks proper API proxy setup for seamless communication\\n3. CORS CONFIGURATION: Python configured for localhost:3000/3001 but needs refinement\\n4. ENVIRONMENT COORDINATION: No shared environment variables between services\\n5. AUTHENTICATION FLOW: No coordinated auth between frontend/backend\\n6. INTEGRATION TESTING: Missing comprehensive test suite for service communication\\n7. PROMPT MANAGEMENT SYSTEM: Section 5 requirements not implemented\\n8. DEPLOYMENT COORDINATION: No unified deployment configuration\\n\\nNEXT ACTIONS:\\n- Fix port coordination and API proxy setup\\n- Implement proper CORS and environment coordination\\n- Create prompt management system\\n- Build integration test suite\\n- Develop unified deployment configuration\"",
      "type": "string",
      "namespace": "default",
      "tags": [],
      "metadata": {},
      "owner": "system",
      "accessLevel": "shared",
      "createdAt": "2025-06-30T19:36:39.300Z",
      "updatedAt": "2025-06-30T19:36:39.300Z",
      "lastAccessedAt": "2025-06-30T19:36:39.300Z",
      "version": 1,
      "size": 1277,
      "compressed": true,
      "checksum": "e0db829b2bbee89687fe8a77259d7230e8f4dfecc0835140996efded5e81f1f5",
      "references": [],
      "dependencies": []
    }
  ],
  "statistics": {
    "overview": {
      "totalEntries": 1,
      "totalSize": 1277,
      "compressedEntries": 1,
      "compressionRatio": 0,
      "indexSize": 50,
      "memoryUsage": 9320656,
      "diskUsage": 0
    },
    "distribution": {
      "byNamespace": {
        "default": {
          "count": 1,
          "size": 1277
        }
      },
      "byType": {
        "string": {
          "count": 1,
          "size": 1277
        }
      },
      "byOwner": {
        "system": {
          "count": 1,
          "size": 1277
        }
      },
      "byAccessLevel": {
        "shared": {
          "count": 1,
          "size": 1277
        }
      }
    },
    "temporal": {
      "entriesCreatedLast24h": 1,
      "entriesUpdatedLast24h": 1,
      "entriesAccessedLast24h": 1,
      "oldestEntry": "2025-06-30T19:36:39.300Z",
      "newestEntry": "2025-06-30T19:36:39.300Z"
    },
    "performance": {
      "averageQueryTime": 0,
      "averageWriteTime": 1,
      "cacheHitRatio": 0,
      "indexEfficiency": 0.95
    },
    "health": {
      "expiredEntries": 0,
      "orphanedReferences": 0,
      "duplicateKeys": 0,
      "corruptedEntries": 0,
      "recommendedCleanup": false
    },
    "optimization": {
      "suggestions": [],
      "potentialSavings": {
        "compression": 0,
        "cleanup": 0,
        "deduplication": 0
      },
      "indexOptimization": [
        "Consider periodic index rebuilding for optimal performance"
      ]
    }
  }
}